{
    "Chinese": {
        "cava.disabled": "服务器已禁用Cava",
        "here.disabled": "服务器已禁用here命令",
        "cava.create.failed": "无法创建Cava",
        "cava.create.failed.alreadyExists": "无法创建Cava:\nCava内容与其他Cava重复",
        "cava.delete.failed": "无法删除最后一个Cava",
        "cava.feedback.deleted": "已删除: %s",
        "cava.feedback.created": "已创建: %s",
        "cava.format": "§b%s\n     §r来自 §e%s",
        "cava.deleted": "玩家 %s(%s) 删除了一个Cava, Cava id: %s",
        "cava.created": "玩家 %s(%s) 创建了一个Cava, Cava id: %s",
        "command.cava.noCava": "无法获取Cava",
        "profile.feedback": "用户设定 \"%s\" 为: %s",
        "dead.receive": "死亡时将收到当时的维度及坐标信息",
        "dead.rejection": "不再接收死亡时的坐标记录信息",
        "dead.deadIn": "你在 %s%s §r死亡: \n §e%s",
        "languages.Chinese": "中文",
        "languages.English": "英文",
        "language.change": "将ModMdo语言切换为 %s",
        "command.here.rejection": "不再接收任何人的/here信息",
        "command.here.receive": "将接收任何人的/here信息",
        "dimension.overworld": "主世界(overworld)",
        "dimension.the_nether": "下界(the_nether)",
        "dimension.the_end": "末地(the_end)",
        "command.here.startWith": "%s 给你发送了一条坐标信息\n",
        "command.here": "%s%s §e在 %s: \n %s",
        "command.dhere": "%s%s §e在 %s: \n %s\n§d转换%s 坐标为 \n %s",
        "command.here.feedback": "将 %s 的位置信息发送到所有玩家",
        "command.here.failed.feedback": "§c无法将位置信息发送到其他玩家"
    },
    "English": {
        "cava.disabled": "server disabled Cava",
        "here.disabled": "server disabled here command",
        "cava.create.failed": "failed to create Cava",
        "cava.create.failed.alreadyExists": "failed to create Cava:\nthe Cava repeat with another Cava",
        "cava.delete.failed": "failed to delete last Cava",
        "cava.feedback.deleted": "deleted Cava: %s",
        "cava.feedback.created": "created Cava: %s",
        "cava.format": "§b%s\n     §rfrom §e%s",
        "cava.deleted": "player %s(%s) deleted a Cava, Cava id: %s",
        "cava.created": "player %s(%s) created a Cava, Cava id: %s",
        "command.cava.noCava": "fail to get Cava",
        "profile.feedback": "user profile \"%s\" is: %s",
        "dead.receive": "receive dimension and position info when dead",
        "dead.rejection": "rejected death record message when dead",
        "dead.deadIn": "you dead in %s%s§r: \n §e%s",
        "languages.Chinese": "chinese",
        "languages.English": "english",
        "language.change": "change the ModMdo language to %s",
        "command.here.rejection": "rejected /here message from anybody",
        "command.here.receive": "receive /here message from anybody",
        "dimension.overworld": "overworld(主世界)",
        "dimension.the_nether": "the_nether(下界)",
        "dimension.the_end": "the_end(末地)",
        "command.here.startWith": "%s send a position message to you\n",
        "command.here": "%s%s §eat %s: \n %s",
        "command.dhere": "%s%s §eat %s: \n %s\n§dConvert %s coordinate is \n %s",
        "command.here.feedback": "sent position of %s to all player",
        "command.here.failed.feedback": "§ccannot send position to other player"
    }
}